setup.py
RimuDNS.egg-info/PKG-INFO
RimuDNS.egg-info/SOURCES.txt
RimuDNS.egg-info/dependency_links.txt
RimuDNS.egg-info/requires.txt
RimuDNS.egg-info/top_level.txt
rimudns/__init__.py
rimudns/consts.py
rimudns/rimudns.py
rimudns/zonehandle.py