Metadata-Version: 1.1
Name: RimuDNS
Version: 0.0.1
Summary: Python interface to RimuHosting/Zonomi DNS 
Home-page: https://github.com/abdallah/RimuDNS
Author: Abdallah Deeb
Author-email: abdallah@deeb.me
License: GPLv3+
Download-URL: https://github.com/abdallah/RimuDNS/zipball/master
Platform: UNKNOWN
Classifier: Development Status :: 4 - Beta
Classifier: Environment :: Console
Classifier: Intended Audience :: Developers
Classifier: License :: OSI Approved :: GNU General Public License v3 or later (GPLv3+)
Classifier: Programming Language :: Python
Classifier: Topic :: Internet :: WWW/HTTP
Classifier: Topic :: Software Development :: Libraries :: Python Modules
Classifier: Topic :: System :: Distributed Computing
Classifier: Topic :: Utilities
